JAE0N_test/__init__.py
zae0n_test-0.0.1.dist-info/METADATA
zae0n_test-0.0.1.dist-info/WHEEL
zae0n_test-0.0.1.dist-info/top_level.txt
zae0n_test-0.0.1.dist-info/RECORD
